dash_mantine_components/Accordion.py
dash_mantine_components/AccordionControl.py
dash_mantine_components/AccordionItem.py
dash_mantine_components/AccordionPanel.py
dash_mantine_components/ActionIcon.py
dash_mantine_components/ActionIconGroup.py
dash_mantine_components/Affix.py
dash_mantine_components/Alert.py
dash_mantine_components/Anchor.py
dash_mantine_components/AppShell.py
dash_mantine_components/AppShellAside.py
dash_mantine_components/AppShellFooter.py
dash_mantine_components/AppShellHeader.py
dash_mantine_components/AppShellMain.py
dash_mantine_components/AppShellNavbar.py
dash_mantine_components/AppShellSection.py
dash_mantine_components/AreaChart.py
dash_mantine_components/AspectRatio.py
dash_mantine_components/Autocomplete.py
dash_mantine_components/Avatar.py
dash_mantine_components/AvatarGroup.py
dash_mantine_components/BackgroundImage.py
dash_mantine_components/Badge.py
dash_mantine_components/BarChart.py
dash_mantine_components/Blockquote.py
dash_mantine_components/Box.py
dash_mantine_components/Breadcrumbs.py
dash_mantine_components/BubbleChart.py
dash_mantine_components/Burger.py
dash_mantine_components/Button.py
dash_mantine_components/ButtonGroup.py
dash_mantine_components/Card.py
dash_mantine_components/CardSection.py
dash_mantine_components/Carousel.py
dash_mantine_components/CarouselSlide.py
dash_mantine_components/Center.py
dash_mantine_components/Checkbox.py
dash_mantine_components/CheckboxCard.py
dash_mantine_components/CheckboxGroup.py
dash_mantine_components/CheckboxIndicator.py
dash_mantine_components/Chip.py
dash_mantine_components/ChipGroup.py
dash_mantine_components/ChipGroupContext.py
dash_mantine_components/Code.py
dash_mantine_components/CodeHighlight.py
dash_mantine_components/CodeHighlightTabs.py
dash_mantine_components/Collapse.py
dash_mantine_components/ColorInput.py
dash_mantine_components/ColorPicker.py
dash_mantine_components/CompositeChart.py
dash_mantine_components/Container.py
dash_mantine_components/CopyButton.py
dash_mantine_components-2.5.1.dist-info/licenses/LICENSE
dash_mantine_components-2.5.1.dist-info/METADATA
dash_mantine_components-2.5.1.dist-info/WHEEL
dash_mantine_components-2.5.1.dist-info/top_level.txt
dash_mantine_components-2.5.1.dist-info/RECORD
