Metadata-Version: 2.4
Name: dash_mantine_components
Version: 2.5.1
Summary: Plotly Dash Components based on Mantine
Home-page: https://github.com/snehilvj/dash-mantine-components
Author: Snehil Vijay <snehilvj@outlook.com>
Author-email: snehilvj@outlook.com
License: MIT
Classifier: Framework :: Dash
Classifier: Framework :: Flask
License-File: LICENSE
Requires-Dist: dash>=2
Provides-Extra: dev
Requires-Dist: dash[ci,dev,testing]>=2; extra == "dev"
Requires-Dist: pyyaml>=5.0; extra == "dev"
Requires-Dist: pytest<8.1.0; extra == "dev"
Requires-Dist: wheel; extra == "dev"
Requires-Dist: selenium<4.3.0; extra == "dev"
Requires-Dist: black; extra == "dev"
Requires-Dist: build; extra == "dev"
Requires-Dist: dash-iconify; extra == "dev"
Dynamic: author
Dynamic: author-email
Dynamic: classifier
Dynamic: description
Dynamic: description-content-type
Dynamic: home-page
Dynamic: license
Dynamic: license-file
Dynamic: provides-extra
Dynamic: requires-dist
Dynamic: summary
